zipline_arrow-3.2.2.dist-info/RECORD
zipline_arrow-3.2.2.dist-info/WHEEL
zipline_arrow-3.2.2.dist-info/entry_points.txt
zipline_arrow-3.2.2.dist-info/top_level.txt
zipline_arrow-3.2.2.dist-info/METADATA
zipline_arrow-3.2.2.dist-info/licenses/LICENSE
zipline_arrow-3.2.2.dist-info/licenses/AUTHORS
zipline/zipline_warnings.py
zipline/algorithm.py
zipline/_protocol.html
zipline/dispatch.py
zipline/protocol.py
zipline/__init__.py
zipline/_protocol.pyx
zipline/api.pyi
zipline/api.py
zipline/extensions.py
zipline/_protocol.c
zipline/_protocol.pxd
zipline/country.py
zipline/errors.py
zipline/currency.py
zipline/__main__.py
zipline/_protocol.cpython-311-darwin.so
zipline/test_algorithms.py
zipline/pipeline/mixins.py
zipline/pipeline/downsample_helpers.py
zipline/pipeline/domain.py
zipline/pipeline/term.py
zipline/pipeline/graph.py
zipline/pipeline/__init__.py
zipline/pipeline/dtypes.py
zipline/pipeline/visualize.py
zipline/pipeline/engine.py
zipline/pipeline/common.py
zipline/pipeline/sentinels.py
zipline/pipeline/pipeline.py
zipline/pipeline/expression.py
zipline/pipeline/api_utils.py
zipline/pipeline/filters/__init__.py
zipline/pipeline/filters/filter.py
zipline/pipeline/filters/smoothing.py
zipline/pipeline/factors/statistical.py
zipline/pipeline/factors/events.py
zipline/pipeline/factors/technical.py
zipline/pipeline/factors/__init__.py
zipline/pipeline/factors/basic.py
zipline/pipeline/factors/factor.py
zipline/pipeline/hooks/iface.py
zipline/pipeline/hooks/__init__.py
zipline/pipeline/hooks/delegate.py
zipline/pipeline/hooks/no.py
zipline/pipeline/hooks/progress.py
zipline/pipeline/hooks/testing.py
zipline/pipeline/data/__init__.py
zipline/pipeline/data/dataset.py
zipline/pipeline/data/equity_pricing.py
zipline/pipeline/data/testing.py
zipline/pipeline/classifiers/classifier.py
zipline/pipeline/classifiers/__init__.py
zipline/pipeline/loaders/earnings_estimates.py
zipline/pipeline/loaders/synthetic.py
zipline/pipeline/loaders/events.py
zipline/pipeline/loaders/__init__.py
zipline/pipeline/loaders/utils.py
zipline/pipeline/loaders/frame.py
zipline/pipeline/loaders/equity_pricing_loader.py
zipline/pipeline/loaders/testing.py
zipline/pipeline/loaders/base.py
