Metadata-Version: 2.4
Name: zipline-arrow
Version: 3.2.2
Summary: A Pythonic backtester for trading algorithms
Author-email: Quantopian Inc <pm@ml4trading.io>, Stefan Jansen <pm@ml4trading.io>
Maintainer-email: Jim White <jim@fovi.com>
License: Apache-2.0
Project-URL: homepage, https://github.com/fovi-llc/zipline-arrow
Project-URL: repository, https://github.com/fovi-llc/zipline-arrow
Project-URL: documentation, https://wiki3.ai/zipline-arrow/
Keywords: backtester,trading,algorithms,finance
Classifier: Development Status :: 4 - Beta
Classifier: License :: OSI Approved :: Apache Software License
Classifier: Natural Language :: English
Classifier: Programming Language :: Python
Classifier: Programming Language :: Python :: 3.10
Classifier: Programming Language :: Python :: 3.11
Classifier: Programming Language :: Python :: 3.12
Classifier: Operating System :: OS Independent
Classifier: Intended Audience :: Science/Research
Classifier: Topic :: Office/Business :: Financial :: Investment
Classifier: Topic :: Scientific/Engineering :: Information Analysis
Classifier: Topic :: System :: Distributed Computing
Requires-Python: <4,>=3.10
License-File: LICENSE
License-File: AUTHORS
Requires-Dist: numpy>=1.23.5; python_version < "3.12"
Requires-Dist: numpy>=1.26.0; python_version >= "3.12"
Requires-Dist: pandas<3.0,>=2.2
Requires-Dist: alembic>=0.7.7
Requires-Dist: bcolz-zipline>=1.2.6
Requires-Dist: bottleneck>=1.0.0
Requires-Dist: click>=4.0.0
Requires-Dist: empyrical-reloaded>=0.5.7
Requires-Dist: h5py>=2.7.1
Requires-Dist: intervaltree>=3
Requires-Dist: iso3166>=2.1.1
Requires-Dist: iso4217>=1.6.20180829
Requires-Dist: lru-dict>=1.1.4
Requires-Dist: multipledispatch>=0.6.0
Requires-Dist: networkx>=2.0
Requires-Dist: numexpr>=2.6.1
Requires-Dist: patsy>=0.4.0
Requires-Dist: python-dateutil>=2.4.2
Requires-Dist: python-interface>=1.5.3
Requires-Dist: pytz>=2018.5
Requires-Dist: requests>=2.9.1
Requires-Dist: scipy>=1.15
Requires-Dist: six>=1.10.0
Requires-Dist: sqlalchemy>=2
Requires-Dist: statsmodels>=0.6.1
Requires-Dist: tables>=3.4.3
Requires-Dist: toolz>=0.8.2
Requires-Dist: exchange-calendars>=4.10
Provides-Extra: test
Requires-Dist: tox; extra == "test"
Requires-Dist: pytest>=8; extra == "test"
Requires-Dist: pytest-cov>=3.0.0; extra == "test"
Requires-Dist: pytest-xdist>=3.6; extra == "test"
Requires-Dist: pytest-timeout>=2; extra == "test"
Requires-Dist: parameterized>=0.8; extra == "test"
Requires-Dist: testfixtures>=4.1.2; extra == "test"
Requires-Dist: flake8>=3.9.1; extra == "test"
Requires-Dist: matplotlib>=1.5.3; extra == "test"
Requires-Dist: responses>=0.9.0; extra == "test"
Requires-Dist: pandas-datareader>=0.2.1; extra == "test"
Requires-Dist: click; extra == "test"
Requires-Dist: coverage; extra == "test"
Requires-Dist: pytest-rerunfailures; extra == "test"
Provides-Extra: dev
Requires-Dist: flake8>=7; extra == "dev"
Requires-Dist: black[jupyter]>=25; extra == "dev"
Requires-Dist: pre-commit>=4.2; extra == "dev"
Requires-Dist: cython>=3; extra == "dev"
Requires-Dist: ruff; extra == "dev"
Provides-Extra: docs
Requires-Dist: cython; extra == "docs"
Requires-Dist: sphinx>=1.3.2; extra == "docs"
Requires-Dist: numpydoc>=0.5.0; extra == "docs"
Requires-Dist: sphinx-autobuild>=0.6.0; extra == "docs"
Requires-Dist: pydata-sphinx-theme; extra == "docs"
Requires-Dist: sphinx_markdown_tables; extra == "docs"
Requires-Dist: m2r2; extra == "docs"
Dynamic: license-file
